cafe/__init__.py
cafe/common/__init__.py
cafe/common/decoding.py
cafe/common/unicode.py
cafe/common/reporting/__init__.py
cafe/common/reporting/base_report.py
cafe/common/reporting/cclogging.py
cafe/common/reporting/json_report.py
cafe/common/reporting/metrics.py
cafe/common/reporting/reporter.py
cafe/common/reporting/subunit_report.py
cafe/common/reporting/xml_report.py
cafe/configurator/__init__.py
cafe/configurator/cli.py
cafe/configurator/managers.py
cafe/drivers/__init__.py
cafe/drivers/base.py
cafe/drivers/behave/__init__.py
cafe/drivers/behave/runner.py
cafe/drivers/lettuce/__init__.py
cafe/drivers/pyvows/__init__.py
cafe/drivers/pyvows/runner.py
cafe/drivers/specter/__init__.py
cafe/drivers/specter/runner.py
cafe/drivers/unittest/__init__.py
cafe/drivers/unittest/arguments.py
cafe/drivers/unittest/autocomplete.py
cafe/drivers/unittest/config.py
cafe/drivers/unittest/datasets.py
cafe/drivers/unittest/decorators.py
cafe/drivers/unittest/fixtures.py
cafe/drivers/unittest/parsers.py
cafe/drivers/unittest/runner.py
cafe/drivers/unittest/runner_parallel.py
cafe/drivers/unittest/suite.py
cafe/drivers/unittest/suite_builder.py
cafe/drivers/unittest/brew/__init__.py
cafe/drivers/unittest/brew/arguments.py
cafe/drivers/unittest/brew/parser.py
cafe/drivers/unittest/brew/runner.py
cafe/engine/__init__.py
cafe/engine/behaviors.py
cafe/engine/config.py
cafe/engine/provider.py
cafe/engine/clients/__init__.py
cafe/engine/clients/base.py
cafe/engine/clients/commandline.py
cafe/engine/clients/ping.py
cafe/engine/clients/sql.py
cafe/engine/models/__init__.py
cafe/engine/models/base.py
cafe/engine/models/behavior_response.py
cafe/engine/models/commandline_response.py
cafe/engine/models/data_interfaces.py
cafe/plugins/elasticsearch/setup.py
cafe/plugins/elasticsearch/cafe/__init__.py
cafe/plugins/elasticsearch/cafe/engine/__init__.py
cafe/plugins/elasticsearch/cafe/engine/clients/__init__.py
opencafe-0.3.5.dist-info/DESCRIPTION.rst
opencafe-0.3.5.dist-info/METADATA
opencafe-0.3.5.dist-info/RECORD
opencafe-0.3.5.dist-info/WHEEL
opencafe-0.3.5.dist-info/entry_points.txt
opencafe-0.3.5.dist-info/metadata.json
opencafe-0.3.5.dist-info/top_level.txt
