Metadata-Version: 2.0
Name: opencafe
Version: 0.3.5
Summary: The Common Automation Framework Engine
Home-page: http://opencafe.readthedocs.org
Author: CafeHub
Author-email: cloud-cafe@lists.rackspace.com
License: # Copyright 2013-2014 Rackspace
Requires-Dist: six
